topojson/__init__.py
topojson/__init__.pyi
topojson/py.typed
topojson/topojson.cpython-312-i386-linux-gnu.so
topojson_rs-0.2.dist-info/METADATA
topojson_rs-0.2.dist-info/WHEEL
topojson_rs-0.2.dist-info/licenses/LICENSE
topojson_rs-0.2.dist-info/RECORD
