Metadata-Version: 2.4
Name: topojson_rs
Version: 0.2
License-File: LICENSE
Summary: Implementation of topojson-client in Rust for creating native Python extension.
Author-email: Benjamin BOURBON <ben.bourbon06@gmail.com>
Project-URL: Documentation, https://topojson-rs.readthedocs.io/en/latest/
Project-URL: Homepage, https://github.com/bourbonut/topojson-rs
Project-URL: Repository, https://github.com/bourbonut/topojson-rs
